assignables/__init__.py
assignables/assignables.py
tests/__init__.py
tests/test.py
assignables-1.0.0.dist-info/LICENSE
assignables-1.0.0.dist-info/METADATA
assignables-1.0.0.dist-info/WHEEL
assignables-1.0.0.dist-info/top_level.txt
assignables-1.0.0.dist-info/RECORD
