Metadata-Version: 2.1
Name: assignables
Version: 1.0.0
Summary: Helper package for assigning values to DB model objects.
Home-page: https://github.com/mijovicpetar/assignables
Author: Petar Mijovic
Author-email: petar@psoftware.co
License: UNKNOWN
Platform: UNKNOWN
Classifier: Programming Language :: Python :: 3
Classifier: License :: OSI Approved :: MIT License
Classifier: Operating System :: OS Independent
